llm_ocr/__init__.py
llm_ocr/config/__init__.py
llm_ocr/config/settings.py
llm_ocr/core/__init__.py
llm_ocr/core/base.py
llm_ocr/core/processor.py
llm_ocr/prompts/__init__.py
llm_ocr/prompts/markdown.py
llm_ocr/providers/__init__.py
llm_ocr/providers/gemini.py
llm_ocr/providers/openai.py
ocr_llm-1.0.0.dist-info/licenses/LICENSE
ocr_llm-1.0.0.dist-info/METADATA
ocr_llm-1.0.0.dist-info/WHEEL
ocr_llm-1.0.0.dist-info/top_level.txt
ocr_llm-1.0.0.dist-info/RECORD
