Metadata-Version: 2.4
Name: ocr-llm
Version: 1.0.0
Summary: Convert PDFs to markdown using Large Language Models (LLMs) with vision capabilities
Author-email: Shehryar Sohail <hafizshehryar88@gmail.com>
License-Expression: MIT
Project-URL: Homepage, https://github.com/Shehryar718/llm-ocr
Project-URL: Repository, https://github.com/Shehryar718/llm-ocr
Project-URL: Issues, https://github.com/Shehryar718/llm-ocr/issues
Keywords: ocr,pdf,markdown,llm,vision,gemini,openai,ai
Classifier: Development Status :: 5 - Production/Stable
Classifier: Intended Audience :: Developers
Classifier: Programming Language :: Python :: 3
Classifier: Programming Language :: Python :: 3.9
Classifier: Programming Language :: Python :: 3.10
Classifier: Programming Language :: Python :: 3.11
Classifier: Programming Language :: Python :: 3.12
Classifier: Topic :: Software Development :: Libraries :: Python Modules
Classifier: Topic :: Text Processing :: Markup :: Markdown
Classifier: Topic :: Multimedia :: Graphics :: Graphics Conversion
Requires-Python: >=3.9
License-File: LICENSE
Requires-Dist: pdf2image>=1.16.0
Requires-Dist: Pillow>=11.0.0
Requires-Dist: google-genai>=1.0.0
Requires-Dist: openai>=2.0.0
Provides-Extra: dev
Requires-Dist: pytest>=8.0.0; extra == "dev"
Requires-Dist: pytest-asyncio>=1.0.0; extra == "dev"
Requires-Dist: pytest-cov>=6.5.0; extra == "dev"
Requires-Dist: pytest-mock>=3.14.0; extra == "dev"
Requires-Dist: black>=24.0.0; extra == "dev"
Requires-Dist: isort>=6.0.0; extra == "dev"
Requires-Dist: flake8>=7.0.0; extra == "dev"
Requires-Dist: mypy>=1.0.0; extra == "dev"
Requires-Dist: ruff>=0.10.0; extra == "dev"
Dynamic: license-file
